crystally/__init__.py
crystally/examples.py
crystally/core/__init__.py
crystally/core/constants.py
crystally/core/lattice.py
crystally/core/vectors.py
crystally/vasp/__init__.py
crystally/vasp/file_handling.py
crystally/vasp/tools.py
Crystally-0.6.1.dist-info/LICENSE.md
Crystally-0.6.1.dist-info/METADATA
Crystally-0.6.1.dist-info/WHEEL
Crystally-0.6.1.dist-info/top_level.txt
Crystally-0.6.1.dist-info/RECORD
