Metadata-Version: 2.1
Name: Crystally
Version: 0.6.1
Summary: Python module to model and analyze crystal structures
Home-page: https://git.rwth-aachen.de/john.arnold/Crystally.git
Author: John Arnold
Author-email: john.arnold@rwth-aachen.de
License: None
Project-URL: Documentation, https://crystally.readthedocs.io/
Requires-Python: >=3.7
License-File: LICENSE.md
Requires-Dist: numpy
Requires-Dist: scipy (>=1.7.0)
